[
    {
        "task_id": "41",
        "study_condition": "4",
        "scenario": "Alice is a sports photographer. Her responsibility involves taking photos of different sports competitions taking place around the city. There was a football match in the stadium [B] at [18:30][T] yesterday, the [30th of September][D]. She was expected to be present 30 minutes earlier for the registration. She also has a limited budget, [X] euro, to commute for her inner-city trips via public transport. Considering that she was at her office at [add time here][T] in location [A] and planning to arrive at [B] on time. What is the best plan that Alice could have followed in terms of minimizing commute time and cost? How could you have best helped her to schedule her commute among the highlighted routes, given the following information? You need to identify which types of public transport (train/bus/taxi) she should have taken respectively and on what stations she might have needed to switch among stations or different types of public transport. Also, calculate the overall time and cost it takes to commute from [A] to [B]. In the next step, an AI system called TripPlanner suggests you the best schedule using one of the highlighted routes. Finally, you finalize your decision in the last step. Note that this AI system is not always accurate. On average, there is one error in every three recommendations that the AI system makes (i.e., the accuracy of the AI system is about ~67%).",
        "complexity": "medium",
        "task_type": "prognostic",
        "best_route_id":"0",
        "best_time": "1",
        "best_cost": "1",
        "ai_route_id":"0",
        "ai_time": "1",
        "ai_cost": "1",
        "map_url_list": "[ 'task_41_route0.html' , 'task_41_route1.html', 'task_41_route2.html', 'task_41_route3.html' , 'task_41_route4.html']",
        "route_info_list": "[{'route': [{'sub_route_name': 'Micheal Allen', 'transport': 'train', 'length': 160.84099999999998, 'duration': 0, 'duration_range': [4.454058461538461, 4.454058461538461], 'capacity_level': 'green', 'traffic': [{'level': 'green', 'nodes': [[52.2867899, 4.8664568], [52.2866628, 4.8670182], [52.286906, 4.8671781], [52.2870209, 4.8672612], [52.2867493, 4.86814], [52.2866856, 4.8682375]]}]}, {'sub_route_name': 'Patience Acosta', 'transport': 'bus', 'length': 850.9110000000001, 'duration': 0, 'duration_range': [47.12737846153846, 55.69599272727273], 'capacity_level': 'red', 'traffic': [{'level': 'green', 'nodes': [[52.2866856, 4.8682375], [52.2869837, 4.8683849], [52.2891856, 4.8677946]]}, {'level': 'orange', 'nodes': [[52.2891856, 4.8677946], [52.2917459, 4.8699172]]}, {'level': 'red', 'nodes': [[52.2917459, 4.8699172], [52.2913677, 4.8713716]]}, {'level': 'orange', 'nodes': [[52.2913677, 4.8713716], [52.2916802, 4.8715753]]}, {'level': 'green', 'nodes': [[52.2916802, 4.8715753], [52.2916306, 4.8717739], [52.2914679, 4.8724536]]}]}, {'sub_route_name': 'Khalil Shaw', 'transport': 'train', 'length': 111.183, 'duration': 0, 'duration_range': [3.078913846153846, 3.078913846153846], 'capacity_level': 'red', 'traffic': [{'level': 'green', 'nodes': [[52.2914679, 4.8724536], [52.2914235, 4.8726389], [52.2911805, 4.8736542], [52.2911035, 4.8739759]]}]}, {'sub_route_name': 'Sam Garner', 'transport': 'taxi', 'length': 203.077, 'duration': 0, 'duration_range': [9.747696000000001, 11.247341538461539], 'capacity_level': 'red', 'traffic': [{'level': 'green', 'nodes': [[52.2911035, 4.8739759], [52.29099, 4.87445], [52.2895801, 4.873544]]}]}], 'route_nodes': [[52.2867899, 4.8664568], [52.2866628, 4.8670182], [52.286906, 4.8671781], [52.2870209, 4.8672612], [52.2867493, 4.86814], [52.2866856, 4.8682375], [52.2869837, 4.8683849], [52.2891856, 4.8677946], [52.2917459, 4.8699172], [52.2913677, 4.8713716], [52.2916802, 4.8715753], [52.2916306, 4.8717739], [52.2914679, 4.8724536], [52.2914235, 4.8726389], [52.2911805, 4.8736542], [52.2911035, 4.8739759], [52.29099, 4.87445], [52.2895801, 4.873544]]}, {'route': [{'sub_route_name': 'Abdullah Whitehead', 'transport': 'taxi', 'length': 199.698, 'duration': 0, 'duration_range': [9.585504, 11.060196923076925], 'capacity_level': 'red', 'traffic': [{'level': 'green', 'nodes': [[52.2867899, 4.8664568], [52.2871612, 4.866683], [52.2870209, 4.8672612], [52.2867493, 4.86814], [52.2866856, 4.8682375], [52.2869837, 4.8683849]]}]}, {'sub_route_name': 'Davian Cross', 'transport': 'bus', 'length': 750.3559999999999, 'duration': 0, 'duration_range': [41.55817846153846, 49.11421090909091], 'capacity_level': 'red', 'traffic': [{'level': 'green', 'nodes': [[52.2869837, 4.8683849], [52.2891856, 4.8677946]]}, {'level': 'orange', 'nodes': [[52.2891856, 4.8677946], [52.2917459, 4.8699172], [52.2913677, 4.8713716], [52.2916802, 4.8715753]]}]}, {'sub_route_name': 'Lawson Fletcher', 'transport': 'taxi', 'length': 175.41500000000002, 'duration': 0, 'duration_range': [8.419920000000001, 9.71529230769231], 'capacity_level': 'orange', 'traffic': [{'level': 'green', 'nodes': [[52.2916802, 4.8715753], [52.2916306, 4.8717739], [52.2914679, 4.8724536], [52.2914235, 4.8726389], [52.2911805, 4.8736542], [52.2911035, 4.8739759]]}]}, {'sub_route_name': 'Emelia Hodge', 'transport': 'train', 'length': 203.077, 'duration': 0, 'duration_range': [5.6236707692307695, 5.6236707692307695], 'capacity_level': 'red', 'traffic': [{'level': 'green', 'nodes': [[52.2911035, 4.8739759], [52.29099, 4.87445], [52.2895801, 4.873544]]}]}], 'route_nodes': [[52.2867899, 4.8664568], [52.2871612, 4.866683], [52.2870209, 4.8672612], [52.2867493, 4.86814], [52.2866856, 4.8682375], [52.2869837, 4.8683849], [52.2891856, 4.8677946], [52.2917459, 4.8699172], [52.2913677, 4.8713716], [52.2916802, 4.8715753], [52.2916306, 4.8717739], [52.2914679, 4.8724536], [52.2914235, 4.8726389], [52.2911805, 4.8736542], [52.2911035, 4.8739759], [52.29099, 4.87445], [52.2895801, 4.873544]]}, {'route': [{'sub_route_name': 'Alexus Caldwell', 'transport': 'train', 'length': 402.28700000000003, 'duration': 0, 'duration_range': [11.140255384615386, 11.140255384615386], 'capacity_level': 'red', 'traffic': [{'level': 'green', 'nodes': [[52.2867899, 4.8664568], [52.2871612, 4.866683], [52.2874659, 4.8668941], [52.2875639, 4.8669545], [52.2883211, 4.8674261], [52.2888314, 4.8664417], [52.2888426, 4.8663977], [52.2889706, 4.8658462], [52.2895426, 4.8662087]]}]}, {'sub_route_name': 'Mekhi Young', 'transport': 'bus', 'length': 436.1719999999999, 'duration': 0, 'duration_range': [24.15721846153846, 28.549439999999997], 'capacity_level': 'red', 'traffic': [{'level': 'green', 'nodes': [[52.2895426, 4.8662087], [52.2891856, 4.8677946], [52.2917459, 4.8699172]]}]}, {'sub_route_name': 'Harley White', 'transport': 'taxi', 'length': 209.131, 'duration': 0, 'duration_range': [10.038288000000001, 11.582640000000001], 'capacity_level': 'orange', 'traffic': [{'level': 'green', 'nodes': [[52.2917459, 4.8699172], [52.2913677, 4.8713716], [52.2916802, 4.8715753]]}, {'level': 'orange', 'nodes': [[52.2916802, 4.8715753], [52.2916306, 4.8717739], [52.2914679, 4.8724536]]}]}, {'sub_route_name': 'Shyann Bates', 'transport': 'train', 'length': 314.26, 'duration': 0, 'duration_range': [8.702584615384616, 8.702584615384616], 'capacity_level': 'orange', 'traffic': [{'level': 'green', 'nodes': [[52.2914679, 4.8724536], [52.2914235, 4.8726389], [52.2911805, 4.8736542], [52.2911035, 4.8739759], [52.29099, 4.87445], [52.2895801, 4.873544]]}]}], 'route_nodes': [[52.2867899, 4.8664568], [52.2871612, 4.866683], [52.2874659, 4.8668941], [52.2875639, 4.8669545], [52.2883211, 4.8674261], [52.2888314, 4.8664417], [52.2888426, 4.8663977], [52.2889706, 4.8658462], [52.2895426, 4.8662087], [52.2891856, 4.8677946], [52.2917459, 4.8699172], [52.2913677, 4.8713716], [52.2916802, 4.8715753], [52.2916306, 4.8717739], [52.2914679, 4.8724536], [52.2914235, 4.8726389], [52.2911805, 4.8736542], [52.2911035, 4.8739759], [52.29099, 4.87445], [52.2895801, 4.873544]]}, {'route': [{'sub_route_name': 'Luciana Warner', 'transport': 'taxi', 'length': 182.611, 'duration': 0, 'duration_range': [8.765328, 10.11384], 'capacity_level': 'green', 'traffic': [{'level': 'orange', 'nodes': [[52.2867899, 4.8664568], [52.2871612, 4.866683]]}, {'level': 'red', 'nodes': [[52.2871612, 4.866683], [52.2874659, 4.8668941], [52.2875639, 4.8669545]]}, {'level': 'orange', 'nodes': [[52.2875639, 4.8669545], [52.2883211, 4.8674261]]}]}, {'sub_route_name': 'Joel Jenkins', 'transport': 'bus', 'length': 766.9209999999999, 'duration': 0, 'duration_range': [42.47562461538461, 50.19846545454545], 'capacity_level': 'red', 'traffic': [{'level': 'red', 'nodes': [[52.2883211, 4.8674261], [52.2888426, 4.8663977], [52.2889706, 4.8658462], [52.2895426, 4.8662087]]}, {'level': 'orange', 'nodes': [[52.2895426, 4.8662087], [52.2891856, 4.8677946]]}, {'level': 'red', 'nodes': [[52.2891856, 4.8677946], [52.2917459, 4.8699172], [52.2913677, 4.8713716]]}]}, {'sub_route_name': 'Marc Rubio', 'transport': 'taxi', 'length': 189.32800000000003, 'duration': 0, 'duration_range': [9.087744000000002, 10.485858461538465], 'capacity_level': 'green', 'traffic': [{'level': 'red', 'nodes': [[52.2913677, 4.8713716], [52.2916802, 4.8715753], [52.2916306, 4.8717739], [52.2914679, 4.8724536], [52.2914235, 4.8726389]]}, {'level': 'orange', 'nodes': [[52.2914235, 4.8726389], [52.2911805, 4.8736542]]}]}, {'sub_route_name': 'Randall Rosales', 'transport': 'bus', 'length': 226.572, 'duration': 0, 'duration_range': [12.548603076923078, 14.830167272727273], 'capacity_level': 'orange', 'traffic': [{'level': 'orange', 'nodes': [[52.2911805, 4.8736542], [52.2911035, 4.8739759]]}, {'level': 'green', 'nodes': [[52.2911035, 4.8739759], [52.29099, 4.87445], [52.2895801, 4.873544]]}]}], 'route_nodes': [[52.2867899, 4.8664568], [52.2871612, 4.866683], [52.2874659, 4.8668941], [52.2875639, 4.8669545], [52.2883211, 4.8674261], [52.2888426, 4.8663977], [52.2889706, 4.8658462], [52.2895426, 4.8662087], [52.2891856, 4.8677946], [52.2917459, 4.8699172], [52.2913677, 4.8713716], [52.2916802, 4.8715753], [52.2916306, 4.8717739], [52.2914679, 4.8724536], [52.2914235, 4.8726389], [52.2911805, 4.8736542], [52.2911035, 4.8739759], [52.29099, 4.87445], [52.2895801, 4.873544]]}, {'route': [{'sub_route_name': 'Luca Garcia', 'transport': 'taxi', 'length': 151.13799999999998, 'duration': 0, 'duration_range': [7.254623999999999, 8.370719999999999], 'capacity_level': 'red', 'traffic': [{'level': 'green', 'nodes': [[52.2867899, 4.8664568], [52.2866628, 4.8670182], [52.286906, 4.8671781], [52.2870209, 4.8672612]]}, {'level': 'orange', 'nodes': [[52.2870209, 4.8672612], [52.2867493, 4.86814]]}]}, {'sub_route_name': 'Amber Tyler', 'transport': 'train', 'length': 46.025999999999996, 'duration': 0, 'duration_range': [1.274566153846154, 1.274566153846154], 'capacity_level': 'red', 'traffic': [{'level': 'green', 'nodes': [[52.2867493, 4.86814], [52.2866856, 4.8682375], [52.2869837, 4.8683849]]}]}, {'sub_route_name': 'Troy Kaufman', 'transport': 'bus', 'length': 977.4689999999998, 'duration': 0, 'duration_range': [54.13674461538461, 63.97978909090908], 'capacity_level': 'orange', 'traffic': [{'level': 'red', 'nodes': [[52.2869837, 4.8683849], [52.2891856, 4.8677946]]}, {'level': 'orange', 'nodes': [[52.2891856, 4.8677946], [52.2917459, 4.8699172], [52.2913677, 4.8713716]]}, {'level': 'green', 'nodes': [[52.2913677, 4.8713716], [52.2897627, 4.8712781]]}]}, {'sub_route_name': 'Micaela Zamora', 'transport': 'train', 'length': 191.105, 'duration': 0, 'duration_range': [5.292138461538461, 5.292138461538461], 'capacity_level': 'green', 'traffic': [{'level': 'green', 'nodes': [[52.2897627, 4.8712781], [52.2895183, 4.8722471], [52.2892544, 4.8733675], [52.2895801, 4.873544]]}]}], 'route_nodes': [[52.2867899, 4.8664568], [52.2866628, 4.8670182], [52.286906, 4.8671781], [52.2870209, 4.8672612], [52.2867493, 4.86814], [52.2866856, 4.8682375], [52.2869837, 4.8683849], [52.2891856, 4.8677946], [52.2917459, 4.8699172], [52.2913677, 4.8713716], [52.2897627, 4.8712781], [52.2895183, 4.8722471], [52.2892544, 4.8733675], [52.2895801, 4.873544]]}]",
        "pickup_point": "[-1,-1]",
        "n_transfer": "3",
        "route_start_time": "[]",
        "static_info": "[{'train': 0.12, 'taxi': 2.5, 'bus': 0.19, 'study_feature': 'actual_cost', 'attr': 'cost' }, {'train': 0, 'taxi': -25, 'bus': -20, 'study_feature': 'rain', 'attr': 'speed_kph' }, {'train': -0.025, 'taxi': -0.25, 'bus': 0, 'study_feature': 'subscription', 'attr': 'cost' } ]",
        "chance_list": "[{'study_feature':'rain', 'chance':50}, {'study_feature':'traffic', 'chance':50}, {'study_feature':'capacity', 'chance':50}, {'study_feature':'pickup_point', 'chance':0}, {'study_feature':'number_transfer', 'chance':0}]"
    },
    {
        "task_id": "42",
        "study_condition": "4",
        "scenario": "Alice is a sports photographer. Her responsibility involves taking photos of different sports competitions taking place around the city. There was a football match in the stadium [B] at [18:30][T] yesterday, the [30th of September][D]. She was expected to be present 30 minutes earlier for the registration. She also has a limited budget, [X] euro, to commute for her inner-city trips via public transport. Considering that she was at her office at [add time here][T] in location [A] and planning to arrive at [B] on time. What is the best plan that Alice could have followed in terms of minimizing commute time and cost? How could you have best helped her to schedule her commute among the highlighted routes, given the following information? You need to identify which types of public transport (train/bus/taxi) she should have taken respectively and on what stations she might have needed to switch among stations or different types of public transport. Also, calculate the overall time and cost it takes to commute from [A] to [B]. In the next step, an AI system called TripPlanner suggests you the best schedule using one of the highlighted routes. Finally, you finalize your decision in the last step. Note that this AI system is not always accurate. On average, there is one error in every three recommendations that the AI system makes (i.e., the accuracy of the AI system is about ~67%).",
        "complexity": "medium",
        "task_type": "prognostic",
        "best_route_id":"0",
        "best_time": "1",
        "best_cost": "1",
        "ai_route_id":"0",
        "ai_time": "1",
        "ai_cost": "1",
        "map_url_list": "['task_42_route0.html' , 'task_42_route1.html', 'task_42_route2.html', 'task_42_route3.html' , 'task_42_route4.html']",
        "route_info_list": "[{'route': [{'sub_route_name': 'Micheal Allen', 'transport': 'train', 'length': 160.84099999999998, 'duration': 0, 'duration_range': [4.454058461538461, 4.454058461538461], 'capacity_level': 'green', 'traffic': [{'level': 'green', 'nodes': [[52.2867899, 4.8664568], [52.2866628, 4.8670182], [52.286906, 4.8671781], [52.2870209, 4.8672612], [52.2867493, 4.86814], [52.2866856, 4.8682375]]}]}, {'sub_route_name': 'Patience Acosta', 'transport': 'bus', 'length': 850.9110000000001, 'duration': 0, 'duration_range': [47.12737846153846, 55.69599272727273], 'capacity_level': 'red', 'traffic': [{'level': 'green', 'nodes': [[52.2866856, 4.8682375], [52.2869837, 4.8683849], [52.2891856, 4.8677946]]}, {'level': 'orange', 'nodes': [[52.2891856, 4.8677946], [52.2917459, 4.8699172]]}, {'level': 'red', 'nodes': [[52.2917459, 4.8699172], [52.2913677, 4.8713716]]}, {'level': 'orange', 'nodes': [[52.2913677, 4.8713716], [52.2916802, 4.8715753]]}, {'level': 'green', 'nodes': [[52.2916802, 4.8715753], [52.2916306, 4.8717739], [52.2914679, 4.8724536]]}]}, {'sub_route_name': 'Khalil Shaw', 'transport': 'train', 'length': 111.183, 'duration': 0, 'duration_range': [3.078913846153846, 3.078913846153846], 'capacity_level': 'red', 'traffic': [{'level': 'green', 'nodes': [[52.2914679, 4.8724536], [52.2914235, 4.8726389], [52.2911805, 4.8736542], [52.2911035, 4.8739759]]}]}, {'sub_route_name': 'Sam Garner', 'transport': 'taxi', 'length': 203.077, 'duration': 0, 'duration_range': [9.747696000000001, 11.247341538461539], 'capacity_level': 'red', 'traffic': [{'level': 'green', 'nodes': [[52.2911035, 4.8739759], [52.29099, 4.87445], [52.2895801, 4.873544]]}]}], 'route_nodes': [[52.2867899, 4.8664568], [52.2866628, 4.8670182], [52.286906, 4.8671781], [52.2870209, 4.8672612], [52.2867493, 4.86814], [52.2866856, 4.8682375], [52.2869837, 4.8683849], [52.2891856, 4.8677946], [52.2917459, 4.8699172], [52.2913677, 4.8713716], [52.2916802, 4.8715753], [52.2916306, 4.8717739], [52.2914679, 4.8724536], [52.2914235, 4.8726389], [52.2911805, 4.8736542], [52.2911035, 4.8739759], [52.29099, 4.87445], [52.2895801, 4.873544]]}, {'route': [{'sub_route_name': 'Abdullah Whitehead', 'transport': 'taxi', 'length': 199.698, 'duration': 0, 'duration_range': [9.585504, 11.060196923076925], 'capacity_level': 'red', 'traffic': [{'level': 'green', 'nodes': [[52.2867899, 4.8664568], [52.2871612, 4.866683], [52.2870209, 4.8672612], [52.2867493, 4.86814], [52.2866856, 4.8682375], [52.2869837, 4.8683849]]}]}, {'sub_route_name': 'Davian Cross', 'transport': 'bus', 'length': 750.3559999999999, 'duration': 0, 'duration_range': [41.55817846153846, 49.11421090909091], 'capacity_level': 'red', 'traffic': [{'level': 'green', 'nodes': [[52.2869837, 4.8683849], [52.2891856, 4.8677946]]}, {'level': 'orange', 'nodes': [[52.2891856, 4.8677946], [52.2917459, 4.8699172], [52.2913677, 4.8713716], [52.2916802, 4.8715753]]}]}, {'sub_route_name': 'Lawson Fletcher', 'transport': 'taxi', 'length': 175.41500000000002, 'duration': 0, 'duration_range': [8.419920000000001, 9.71529230769231], 'capacity_level': 'orange', 'traffic': [{'level': 'green', 'nodes': [[52.2916802, 4.8715753], [52.2916306, 4.8717739], [52.2914679, 4.8724536], [52.2914235, 4.8726389], [52.2911805, 4.8736542], [52.2911035, 4.8739759]]}]}, {'sub_route_name': 'Emelia Hodge', 'transport': 'train', 'length': 203.077, 'duration': 0, 'duration_range': [5.6236707692307695, 5.6236707692307695], 'capacity_level': 'red', 'traffic': [{'level': 'green', 'nodes': [[52.2911035, 4.8739759], [52.29099, 4.87445], [52.2895801, 4.873544]]}]}], 'route_nodes': [[52.2867899, 4.8664568], [52.2871612, 4.866683], [52.2870209, 4.8672612], [52.2867493, 4.86814], [52.2866856, 4.8682375], [52.2869837, 4.8683849], [52.2891856, 4.8677946], [52.2917459, 4.8699172], [52.2913677, 4.8713716], [52.2916802, 4.8715753], [52.2916306, 4.8717739], [52.2914679, 4.8724536], [52.2914235, 4.8726389], [52.2911805, 4.8736542], [52.2911035, 4.8739759], [52.29099, 4.87445], [52.2895801, 4.873544]]}, {'route': [{'sub_route_name': 'Alexus Caldwell', 'transport': 'train', 'length': 402.28700000000003, 'duration': 0, 'duration_range': [11.140255384615386, 11.140255384615386], 'capacity_level': 'red', 'traffic': [{'level': 'green', 'nodes': [[52.2867899, 4.8664568], [52.2871612, 4.866683], [52.2874659, 4.8668941], [52.2875639, 4.8669545], [52.2883211, 4.8674261], [52.2888314, 4.8664417], [52.2888426, 4.8663977], [52.2889706, 4.8658462], [52.2895426, 4.8662087]]}]}, {'sub_route_name': 'Mekhi Young', 'transport': 'bus', 'length': 436.1719999999999, 'duration': 0, 'duration_range': [24.15721846153846, 28.549439999999997], 'capacity_level': 'red', 'traffic': [{'level': 'green', 'nodes': [[52.2895426, 4.8662087], [52.2891856, 4.8677946], [52.2917459, 4.8699172]]}]}, {'sub_route_name': 'Harley White', 'transport': 'taxi', 'length': 209.131, 'duration': 0, 'duration_range': [10.038288000000001, 11.582640000000001], 'capacity_level': 'orange', 'traffic': [{'level': 'green', 'nodes': [[52.2917459, 4.8699172], [52.2913677, 4.8713716], [52.2916802, 4.8715753]]}, {'level': 'orange', 'nodes': [[52.2916802, 4.8715753], [52.2916306, 4.8717739], [52.2914679, 4.8724536]]}]}, {'sub_route_name': 'Shyann Bates', 'transport': 'train', 'length': 314.26, 'duration': 0, 'duration_range': [8.702584615384616, 8.702584615384616], 'capacity_level': 'orange', 'traffic': [{'level': 'green', 'nodes': [[52.2914679, 4.8724536], [52.2914235, 4.8726389], [52.2911805, 4.8736542], [52.2911035, 4.8739759], [52.29099, 4.87445], [52.2895801, 4.873544]]}]}], 'route_nodes': [[52.2867899, 4.8664568], [52.2871612, 4.866683], [52.2874659, 4.8668941], [52.2875639, 4.8669545], [52.2883211, 4.8674261], [52.2888314, 4.8664417], [52.2888426, 4.8663977], [52.2889706, 4.8658462], [52.2895426, 4.8662087], [52.2891856, 4.8677946], [52.2917459, 4.8699172], [52.2913677, 4.8713716], [52.2916802, 4.8715753], [52.2916306, 4.8717739], [52.2914679, 4.8724536], [52.2914235, 4.8726389], [52.2911805, 4.8736542], [52.2911035, 4.8739759], [52.29099, 4.87445], [52.2895801, 4.873544]]}, {'route': [{'sub_route_name': 'Luciana Warner', 'transport': 'taxi', 'length': 182.611, 'duration': 0, 'duration_range': [8.765328, 10.11384], 'capacity_level': 'green', 'traffic': [{'level': 'orange', 'nodes': [[52.2867899, 4.8664568], [52.2871612, 4.866683]]}, {'level': 'red', 'nodes': [[52.2871612, 4.866683], [52.2874659, 4.8668941], [52.2875639, 4.8669545]]}, {'level': 'orange', 'nodes': [[52.2875639, 4.8669545], [52.2883211, 4.8674261]]}]}, {'sub_route_name': 'Joel Jenkins', 'transport': 'bus', 'length': 766.9209999999999, 'duration': 0, 'duration_range': [42.47562461538461, 50.19846545454545], 'capacity_level': 'red', 'traffic': [{'level': 'red', 'nodes': [[52.2883211, 4.8674261], [52.2888426, 4.8663977], [52.2889706, 4.8658462], [52.2895426, 4.8662087]]}, {'level': 'orange', 'nodes': [[52.2895426, 4.8662087], [52.2891856, 4.8677946]]}, {'level': 'red', 'nodes': [[52.2891856, 4.8677946], [52.2917459, 4.8699172], [52.2913677, 4.8713716]]}]}, {'sub_route_name': 'Marc Rubio', 'transport': 'taxi', 'length': 189.32800000000003, 'duration': 0, 'duration_range': [9.087744000000002, 10.485858461538465], 'capacity_level': 'green', 'traffic': [{'level': 'red', 'nodes': [[52.2913677, 4.8713716], [52.2916802, 4.8715753], [52.2916306, 4.8717739], [52.2914679, 4.8724536], [52.2914235, 4.8726389]]}, {'level': 'orange', 'nodes': [[52.2914235, 4.8726389], [52.2911805, 4.8736542]]}]}, {'sub_route_name': 'Randall Rosales', 'transport': 'bus', 'length': 226.572, 'duration': 0, 'duration_range': [12.548603076923078, 14.830167272727273], 'capacity_level': 'orange', 'traffic': [{'level': 'orange', 'nodes': [[52.2911805, 4.8736542], [52.2911035, 4.8739759]]}, {'level': 'green', 'nodes': [[52.2911035, 4.8739759], [52.29099, 4.87445], [52.2895801, 4.873544]]}]}], 'route_nodes': [[52.2867899, 4.8664568], [52.2871612, 4.866683], [52.2874659, 4.8668941], [52.2875639, 4.8669545], [52.2883211, 4.8674261], [52.2888426, 4.8663977], [52.2889706, 4.8658462], [52.2895426, 4.8662087], [52.2891856, 4.8677946], [52.2917459, 4.8699172], [52.2913677, 4.8713716], [52.2916802, 4.8715753], [52.2916306, 4.8717739], [52.2914679, 4.8724536], [52.2914235, 4.8726389], [52.2911805, 4.8736542], [52.2911035, 4.8739759], [52.29099, 4.87445], [52.2895801, 4.873544]]}, {'route': [{'sub_route_name': 'Luca Garcia', 'transport': 'taxi', 'length': 151.13799999999998, 'duration': 0, 'duration_range': [7.254623999999999, 8.370719999999999], 'capacity_level': 'red', 'traffic': [{'level': 'green', 'nodes': [[52.2867899, 4.8664568], [52.2866628, 4.8670182], [52.286906, 4.8671781], [52.2870209, 4.8672612]]}, {'level': 'orange', 'nodes': [[52.2870209, 4.8672612], [52.2867493, 4.86814]]}]}, {'sub_route_name': 'Amber Tyler', 'transport': 'train', 'length': 46.025999999999996, 'duration': 0, 'duration_range': [1.274566153846154, 1.274566153846154], 'capacity_level': 'red', 'traffic': [{'level': 'green', 'nodes': [[52.2867493, 4.86814], [52.2866856, 4.8682375], [52.2869837, 4.8683849]]}]}, {'sub_route_name': 'Troy Kaufman', 'transport': 'bus', 'length': 977.4689999999998, 'duration': 0, 'duration_range': [54.13674461538461, 63.97978909090908], 'capacity_level': 'orange', 'traffic': [{'level': 'red', 'nodes': [[52.2869837, 4.8683849], [52.2891856, 4.8677946]]}, {'level': 'orange', 'nodes': [[52.2891856, 4.8677946], [52.2917459, 4.8699172], [52.2913677, 4.8713716]]}, {'level': 'green', 'nodes': [[52.2913677, 4.8713716], [52.2897627, 4.8712781]]}]}, {'sub_route_name': 'Micaela Zamora', 'transport': 'train', 'length': 191.105, 'duration': 0, 'duration_range': [5.292138461538461, 5.292138461538461], 'capacity_level': 'green', 'traffic': [{'level': 'green', 'nodes': [[52.2897627, 4.8712781], [52.2895183, 4.8722471], [52.2892544, 4.8733675], [52.2895801, 4.873544]]}]}], 'route_nodes': [[52.2867899, 4.8664568], [52.2866628, 4.8670182], [52.286906, 4.8671781], [52.2870209, 4.8672612], [52.2867493, 4.86814], [52.2866856, 4.8682375], [52.2869837, 4.8683849], [52.2891856, 4.8677946], [52.2917459, 4.8699172], [52.2913677, 4.8713716], [52.2897627, 4.8712781], [52.2895183, 4.8722471], [52.2892544, 4.8733675], [52.2895801, 4.873544]]}]",
        "pickup_point": "[-1,-1]",
        "n_transfer": "3",
        "route_start_time": "[]",
        "static_info": "[{'train': 0.12, 'taxi': 2.5, 'bus': 0.19, 'study_feature': 'actual_cost', 'attr': 'cost' }, {'train': 0, 'taxi': -25, 'bus': -20, 'study_feature': 'rain', 'attr': 'speed_kph' }, {'train': -0.025, 'taxi': -0.25, 'bus': 0, 'study_feature': 'subscription', 'attr': 'cost' } ]",
        "chance_list": "[{'study_feature':'rain', 'chance':50}, {'study_feature':'traffic', 'chance':50}, {'study_feature':'capacity', 'chance':50}, {'study_feature':'pickup_point', 'chance':0}, {'study_feature':'number_transfer', 'chance':0}]"
    },
    {
        "task_id": "41",
        "study_condition": "4",
        "scenario": "Alice is a sports photographer. Her responsibility involves taking photos of different sports competitions taking place around the city. There was a football match in the stadium [B] at [18:30][T] yesterday, the [30th of September][D]. She was expected to be present 30 minutes earlier for the registration. She also has a limited budget, [X] euro, to commute for her inner-city trips via public transport. Considering that she was at her office at [add time here][T] in location [A] and planning to arrive at [B] on time. What is the best plan that Alice could have followed in terms of minimizing commute time and cost? How could you have best helped her to schedule her commute among the highlighted routes, given the following information? You need to identify which types of public transport (train/bus/taxi) she should have taken respectively and on what stations she might have needed to switch among stations or different types of public transport. Also, calculate the overall time and cost it takes to commute from [A] to [B]. In the next step, an AI system called TripPlanner suggests you the best schedule using one of the highlighted routes. Finally, you finalize your decision in the last step. Note that this AI system is not always accurate. On average, there is one error in every three recommendations that the AI system makes (i.e., the accuracy of the AI system is about ~67%).",
        "complexity": "medium",
        "task_type": "prognostic",
        "best_route_id":"0",
        "best_time": "1",
        "best_cost": "1",
        "ai_route_id":"0",
        "ai_time": "1",
        "ai_cost": "1",
        "map_url_list": "[ 'task_43_route0.html' , 'task_43_route1.html', 'task_43_route2.html', 'task_43_route3.html' , 'task_43_route4.html']",
        "route_info_list": "[{'route': [{'sub_route_name': 'Micheal Allen', 'transport': 'train', 'length': 160.84099999999998, 'duration': 0, 'duration_range': [4.454058461538461, 4.454058461538461], 'capacity_level': 'green', 'traffic': [{'level': 'green', 'nodes': [[52.2867899, 4.8664568], [52.2866628, 4.8670182], [52.286906, 4.8671781], [52.2870209, 4.8672612], [52.2867493, 4.86814], [52.2866856, 4.8682375]]}]}, {'sub_route_name': 'Patience Acosta', 'transport': 'bus', 'length': 850.9110000000001, 'duration': 0, 'duration_range': [47.12737846153846, 55.69599272727273], 'capacity_level': 'red', 'traffic': [{'level': 'green', 'nodes': [[52.2866856, 4.8682375], [52.2869837, 4.8683849], [52.2891856, 4.8677946]]}, {'level': 'orange', 'nodes': [[52.2891856, 4.8677946], [52.2917459, 4.8699172]]}, {'level': 'red', 'nodes': [[52.2917459, 4.8699172], [52.2913677, 4.8713716]]}, {'level': 'orange', 'nodes': [[52.2913677, 4.8713716], [52.2916802, 4.8715753]]}, {'level': 'green', 'nodes': [[52.2916802, 4.8715753], [52.2916306, 4.8717739], [52.2914679, 4.8724536]]}]}, {'sub_route_name': 'Khalil Shaw', 'transport': 'train', 'length': 111.183, 'duration': 0, 'duration_range': [3.078913846153846, 3.078913846153846], 'capacity_level': 'red', 'traffic': [{'level': 'green', 'nodes': [[52.2914679, 4.8724536], [52.2914235, 4.8726389], [52.2911805, 4.8736542], [52.2911035, 4.8739759]]}]}, {'sub_route_name': 'Sam Garner', 'transport': 'taxi', 'length': 203.077, 'duration': 0, 'duration_range': [9.747696000000001, 11.247341538461539], 'capacity_level': 'red', 'traffic': [{'level': 'green', 'nodes': [[52.2911035, 4.8739759], [52.29099, 4.87445], [52.2895801, 4.873544]]}]}], 'route_nodes': [[52.2867899, 4.8664568], [52.2866628, 4.8670182], [52.286906, 4.8671781], [52.2870209, 4.8672612], [52.2867493, 4.86814], [52.2866856, 4.8682375], [52.2869837, 4.8683849], [52.2891856, 4.8677946], [52.2917459, 4.8699172], [52.2913677, 4.8713716], [52.2916802, 4.8715753], [52.2916306, 4.8717739], [52.2914679, 4.8724536], [52.2914235, 4.8726389], [52.2911805, 4.8736542], [52.2911035, 4.8739759], [52.29099, 4.87445], [52.2895801, 4.873544]]}, {'route': [{'sub_route_name': 'Abdullah Whitehead', 'transport': 'taxi', 'length': 199.698, 'duration': 0, 'duration_range': [9.585504, 11.060196923076925], 'capacity_level': 'red', 'traffic': [{'level': 'green', 'nodes': [[52.2867899, 4.8664568], [52.2871612, 4.866683], [52.2870209, 4.8672612], [52.2867493, 4.86814], [52.2866856, 4.8682375], [52.2869837, 4.8683849]]}]}, {'sub_route_name': 'Davian Cross', 'transport': 'bus', 'length': 750.3559999999999, 'duration': 0, 'duration_range': [41.55817846153846, 49.11421090909091], 'capacity_level': 'red', 'traffic': [{'level': 'green', 'nodes': [[52.2869837, 4.8683849], [52.2891856, 4.8677946]]}, {'level': 'orange', 'nodes': [[52.2891856, 4.8677946], [52.2917459, 4.8699172], [52.2913677, 4.8713716], [52.2916802, 4.8715753]]}]}, {'sub_route_name': 'Lawson Fletcher', 'transport': 'taxi', 'length': 175.41500000000002, 'duration': 0, 'duration_range': [8.419920000000001, 9.71529230769231], 'capacity_level': 'orange', 'traffic': [{'level': 'green', 'nodes': [[52.2916802, 4.8715753], [52.2916306, 4.8717739], [52.2914679, 4.8724536], [52.2914235, 4.8726389], [52.2911805, 4.8736542], [52.2911035, 4.8739759]]}]}, {'sub_route_name': 'Emelia Hodge', 'transport': 'train', 'length': 203.077, 'duration': 0, 'duration_range': [5.6236707692307695, 5.6236707692307695], 'capacity_level': 'red', 'traffic': [{'level': 'green', 'nodes': [[52.2911035, 4.8739759], [52.29099, 4.87445], [52.2895801, 4.873544]]}]}], 'route_nodes': [[52.2867899, 4.8664568], [52.2871612, 4.866683], [52.2870209, 4.8672612], [52.2867493, 4.86814], [52.2866856, 4.8682375], [52.2869837, 4.8683849], [52.2891856, 4.8677946], [52.2917459, 4.8699172], [52.2913677, 4.8713716], [52.2916802, 4.8715753], [52.2916306, 4.8717739], [52.2914679, 4.8724536], [52.2914235, 4.8726389], [52.2911805, 4.8736542], [52.2911035, 4.8739759], [52.29099, 4.87445], [52.2895801, 4.873544]]}, {'route': [{'sub_route_name': 'Alexus Caldwell', 'transport': 'train', 'length': 402.28700000000003, 'duration': 0, 'duration_range': [11.140255384615386, 11.140255384615386], 'capacity_level': 'red', 'traffic': [{'level': 'green', 'nodes': [[52.2867899, 4.8664568], [52.2871612, 4.866683], [52.2874659, 4.8668941], [52.2875639, 4.8669545], [52.2883211, 4.8674261], [52.2888314, 4.8664417], [52.2888426, 4.8663977], [52.2889706, 4.8658462], [52.2895426, 4.8662087]]}]}, {'sub_route_name': 'Mekhi Young', 'transport': 'bus', 'length': 436.1719999999999, 'duration': 0, 'duration_range': [24.15721846153846, 28.549439999999997], 'capacity_level': 'red', 'traffic': [{'level': 'green', 'nodes': [[52.2895426, 4.8662087], [52.2891856, 4.8677946], [52.2917459, 4.8699172]]}]}, {'sub_route_name': 'Harley White', 'transport': 'taxi', 'length': 209.131, 'duration': 0, 'duration_range': [10.038288000000001, 11.582640000000001], 'capacity_level': 'orange', 'traffic': [{'level': 'green', 'nodes': [[52.2917459, 4.8699172], [52.2913677, 4.8713716], [52.2916802, 4.8715753]]}, {'level': 'orange', 'nodes': [[52.2916802, 4.8715753], [52.2916306, 4.8717739], [52.2914679, 4.8724536]]}]}, {'sub_route_name': 'Shyann Bates', 'transport': 'train', 'length': 314.26, 'duration': 0, 'duration_range': [8.702584615384616, 8.702584615384616], 'capacity_level': 'orange', 'traffic': [{'level': 'green', 'nodes': [[52.2914679, 4.8724536], [52.2914235, 4.8726389], [52.2911805, 4.8736542], [52.2911035, 4.8739759], [52.29099, 4.87445], [52.2895801, 4.873544]]}]}], 'route_nodes': [[52.2867899, 4.8664568], [52.2871612, 4.866683], [52.2874659, 4.8668941], [52.2875639, 4.8669545], [52.2883211, 4.8674261], [52.2888314, 4.8664417], [52.2888426, 4.8663977], [52.2889706, 4.8658462], [52.2895426, 4.8662087], [52.2891856, 4.8677946], [52.2917459, 4.8699172], [52.2913677, 4.8713716], [52.2916802, 4.8715753], [52.2916306, 4.8717739], [52.2914679, 4.8724536], [52.2914235, 4.8726389], [52.2911805, 4.8736542], [52.2911035, 4.8739759], [52.29099, 4.87445], [52.2895801, 4.873544]]}, {'route': [{'sub_route_name': 'Luciana Warner', 'transport': 'taxi', 'length': 182.611, 'duration': 0, 'duration_range': [8.765328, 10.11384], 'capacity_level': 'green', 'traffic': [{'level': 'orange', 'nodes': [[52.2867899, 4.8664568], [52.2871612, 4.866683]]}, {'level': 'red', 'nodes': [[52.2871612, 4.866683], [52.2874659, 4.8668941], [52.2875639, 4.8669545]]}, {'level': 'orange', 'nodes': [[52.2875639, 4.8669545], [52.2883211, 4.8674261]]}]}, {'sub_route_name': 'Joel Jenkins', 'transport': 'bus', 'length': 766.9209999999999, 'duration': 0, 'duration_range': [42.47562461538461, 50.19846545454545], 'capacity_level': 'red', 'traffic': [{'level': 'red', 'nodes': [[52.2883211, 4.8674261], [52.2888426, 4.8663977], [52.2889706, 4.8658462], [52.2895426, 4.8662087]]}, {'level': 'orange', 'nodes': [[52.2895426, 4.8662087], [52.2891856, 4.8677946]]}, {'level': 'red', 'nodes': [[52.2891856, 4.8677946], [52.2917459, 4.8699172], [52.2913677, 4.8713716]]}]}, {'sub_route_name': 'Marc Rubio', 'transport': 'taxi', 'length': 189.32800000000003, 'duration': 0, 'duration_range': [9.087744000000002, 10.485858461538465], 'capacity_level': 'green', 'traffic': [{'level': 'red', 'nodes': [[52.2913677, 4.8713716], [52.2916802, 4.8715753], [52.2916306, 4.8717739], [52.2914679, 4.8724536], [52.2914235, 4.8726389]]}, {'level': 'orange', 'nodes': [[52.2914235, 4.8726389], [52.2911805, 4.8736542]]}]}, {'sub_route_name': 'Randall Rosales', 'transport': 'bus', 'length': 226.572, 'duration': 0, 'duration_range': [12.548603076923078, 14.830167272727273], 'capacity_level': 'orange', 'traffic': [{'level': 'orange', 'nodes': [[52.2911805, 4.8736542], [52.2911035, 4.8739759]]}, {'level': 'green', 'nodes': [[52.2911035, 4.8739759], [52.29099, 4.87445], [52.2895801, 4.873544]]}]}], 'route_nodes': [[52.2867899, 4.8664568], [52.2871612, 4.866683], [52.2874659, 4.8668941], [52.2875639, 4.8669545], [52.2883211, 4.8674261], [52.2888426, 4.8663977], [52.2889706, 4.8658462], [52.2895426, 4.8662087], [52.2891856, 4.8677946], [52.2917459, 4.8699172], [52.2913677, 4.8713716], [52.2916802, 4.8715753], [52.2916306, 4.8717739], [52.2914679, 4.8724536], [52.2914235, 4.8726389], [52.2911805, 4.8736542], [52.2911035, 4.8739759], [52.29099, 4.87445], [52.2895801, 4.873544]]}, {'route': [{'sub_route_name': 'Luca Garcia', 'transport': 'taxi', 'length': 151.13799999999998, 'duration': 0, 'duration_range': [7.254623999999999, 8.370719999999999], 'capacity_level': 'red', 'traffic': [{'level': 'green', 'nodes': [[52.2867899, 4.8664568], [52.2866628, 4.8670182], [52.286906, 4.8671781], [52.2870209, 4.8672612]]}, {'level': 'orange', 'nodes': [[52.2870209, 4.8672612], [52.2867493, 4.86814]]}]}, {'sub_route_name': 'Amber Tyler', 'transport': 'train', 'length': 46.025999999999996, 'duration': 0, 'duration_range': [1.274566153846154, 1.274566153846154], 'capacity_level': 'red', 'traffic': [{'level': 'green', 'nodes': [[52.2867493, 4.86814], [52.2866856, 4.8682375], [52.2869837, 4.8683849]]}]}, {'sub_route_name': 'Troy Kaufman', 'transport': 'bus', 'length': 977.4689999999998, 'duration': 0, 'duration_range': [54.13674461538461, 63.97978909090908], 'capacity_level': 'orange', 'traffic': [{'level': 'red', 'nodes': [[52.2869837, 4.8683849], [52.2891856, 4.8677946]]}, {'level': 'orange', 'nodes': [[52.2891856, 4.8677946], [52.2917459, 4.8699172], [52.2913677, 4.8713716]]}, {'level': 'green', 'nodes': [[52.2913677, 4.8713716], [52.2897627, 4.8712781]]}]}, {'sub_route_name': 'Micaela Zamora', 'transport': 'train', 'length': 191.105, 'duration': 0, 'duration_range': [5.292138461538461, 5.292138461538461], 'capacity_level': 'green', 'traffic': [{'level': 'green', 'nodes': [[52.2897627, 4.8712781], [52.2895183, 4.8722471], [52.2892544, 4.8733675], [52.2895801, 4.873544]]}]}], 'route_nodes': [[52.2867899, 4.8664568], [52.2866628, 4.8670182], [52.286906, 4.8671781], [52.2870209, 4.8672612], [52.2867493, 4.86814], [52.2866856, 4.8682375], [52.2869837, 4.8683849], [52.2891856, 4.8677946], [52.2917459, 4.8699172], [52.2913677, 4.8713716], [52.2897627, 4.8712781], [52.2895183, 4.8722471], [52.2892544, 4.8733675], [52.2895801, 4.873544]]}]",
        "pickup_point": "[-1,-1]",
        "n_transfer": "3",
        "route_start_time": "[]",
        "static_info": "[{'train': 0.12, 'taxi': 2.5, 'bus': 0.19, 'study_feature': 'actual_cost', 'attr': 'cost' }, {'train': 0, 'taxi': -25, 'bus': -20, 'study_feature': 'rain', 'attr': 'speed_kph' }, {'train': -0.025, 'taxi': -0.25, 'bus': 0, 'study_feature': 'subscription', 'attr': 'cost' } ]",
        "chance_list": "[{'study_feature':'rain', 'chance':50}, {'study_feature':'traffic', 'chance':50}, {'study_feature':'capacity', 'chance':50}, {'study_feature':'pickup_point', 'chance':0}, {'study_feature':'number_transfer', 'chance':0}]"
    }
]